luxeprint-1.1.0.dist-info/METADATA
luxeprint-1.1.0.dist-info/WHEEL
luxeprint/__init__.py
luxeprint/luxeprint.cpython-312-darwin.so
luxeprint-1.1.0.dist-info/RECORD
