Metadata-Version: 2.3
Name: luxeprint
Version: 1.1.0
Classifier: Programming Language :: Rust
Classifier: Programming Language :: Python :: Implementation :: CPython
Classifier: Programming Language :: Python :: Implementation :: PyPy
Classifier: Development Status :: 5 - Production/Stable
Classifier: Intended Audience :: Developers
Classifier: Intended Audience :: Education
Classifier: Intended Audience :: Science/Research
Classifier: Operating System :: OS Independent
Classifier: Programming Language :: Python :: 3
Classifier: Programming Language :: Python :: 3.9
Classifier: Programming Language :: Python :: 3.10
Classifier: Programming Language :: Python :: 3.11
Classifier: Programming Language :: Python :: 3.12
Classifier: Programming Language :: Python :: 3.13
Summary: A Rust-based library for styled printing, tables, and emojis.
Home-Page: https://github.com/TezRomacH/luxeprint
Author: Roman Tezikov <tez.romach@gmail.com>
Author-email: Roman Tezikov <tez.romach@gmail.com>
License: MIT
Requires-Python: >=3.9
Project-URL: homepage, https://github.com/TezRomacH/luxeprint
Project-URL: repository, https://github.com/TezRomacH/luxeprint
